flask_openvidu/__init__.py
flask_openvidu/flask_openvidu.py
flask_openvidu-0.1.0.dist-info/AUTHORS.rst
flask_openvidu-0.1.0.dist-info/LICENSE
flask_openvidu-0.1.0.dist-info/METADATA
flask_openvidu-0.1.0.dist-info/WHEEL
flask_openvidu-0.1.0.dist-info/top_level.txt
flask_openvidu-0.1.0.dist-info/RECORD
