Metadata-Version: 2.1
Name: flask-openvidu
Version: 0.1.0
Summary: Adds OpenVidu support to your Flask application
Home-page: https://github.com/marcsello/flask-openvidu
Author: Marcell Pünkösd
Author-email: punkosdmarcell@rocketmail.com
License: MIT license
Project-URL: Documentation, https://flask-openvidu.readthedocs.io/
Project-URL: Code, https://github.com/marcsello/flask-openvidu
Project-URL: Issue tracker, https://github.com/marcsello/flask-openvidu
Keywords: flask_openvidu
Platform: UNKNOWN
Classifier: Development Status :: 2 - Pre-Alpha
Classifier: Intended Audience :: Developers
Classifier: License :: OSI Approved :: MIT License
Classifier: Natural Language :: English
Classifier: Programming Language :: Python
Classifier: Programming Language :: Python :: 3
Classifier: Programming Language :: Python :: 3.7
Classifier: Programming Language :: Python :: 3.8
Classifier: Framework :: Flask
Classifier: Topic :: Software Development :: Libraries :: Python Modules
Requires-Python: >=3.7
Requires-Dist: pyopenvidu (>=0.1.3)
Requires-Dist: flask
